freewayai/__init__.py
freewayai/database_query_template_format.py
freewayai/llm_system.py
freewayai/prompt_messages_to_provider_format.py
freewayai/prompt_template.py
freewayai/system_logger.py
freewayai/token_counting.py
freewayai/utilities.py
freewayai-0.1.3.dist-info/LICENSE
freewayai-0.1.3.dist-info/METADATA
freewayai-0.1.3.dist-info/WHEEL
freewayai-0.1.3.dist-info/top_level.txt
freewayai-0.1.3.dist-info/RECORD
