Metadata-Version: 2.1
Name: freewayai
Version: 0.1.3
Summary: A new open-standard specification for LLM-backed systems and an SDK for building on it
Author-email: Ben Parfitt <ben@diligently.ai>, Michael Cox <michael@diligently.ai>
Project-URL: Homepage, https://github.com/diligentlyai/freewayai
Project-URL: Issues, https://github.com/diligentlyai/freewayai/issues
Classifier: Programming Language :: Python :: 3
Classifier: License :: OSI Approved :: MIT License
Classifier: Operating System :: OS Independent
Requires-Python: >=3.9
License-File: LICENSE
Requires-Dist: tiktoken
